kyle_add_mcp/__init__.py
kyle_add_mcp-0.1.0.dist-info/METADATA
kyle_add_mcp-0.1.0.dist-info/WHEEL
kyle_add_mcp-0.1.0.dist-info/entry_points.txt
kyle_add_mcp-0.1.0.dist-info/RECORD
