Metadata-Version: 2.4
Name: kyle-add-mcp
Version: 0.1.0
Summary: Add your description here
Author-email: kyle <2497725756@qq.com>
Requires-Python: >=3.13
Requires-Dist: mcp[cli]>=1.9.3
